{".class": "MypyFile", "_fullname": "myutils.FILECONSTANTS", "future_import_flags": [], "is_partial_stub_package": false, "is_stub": false, "names": {".class": "SymbolTable", "AREAS": {".class": "SymbolTableNode", "kind": "Gdef", "node": {".class": "Var", "flags": ["is_inferred", "has_explicit_value"], "fullname": "myutils.FILECONSTANTS.AREAS", "name": "AREAS", "type": {".class": "Instance", "args": [{".class": "AnyType", "missing_import_name": null, "source_any": null, "type_of_any": 4}, {".class": "AnyType", "missing_import_name": null, "source_any": null, "type_of_any": 4}], "type_ref": "builtins.dict"}}}, "CONST": {".class": "SymbolTableNode", "cross_ref": "myutils.CONSTANTS", "kind": "Gdef"}, "EXTERNALS": {".class": "SymbolTableNode", "kind": "Gdef", "node": {".class": "Var", "flags": ["is_inferred", "has_explicit_value"], "fullname": "myutils.FILECONSTANTS.EXTERNALS", "name": "EXTERNALS", "type": {".class": "Instance", "args": [{".class": "AnyType", "missing_import_name": null, "source_any": {".class": "AnyType", "missing_import_name": null, "source_any": null, "type_of_any": 4}, "type_of_any": 7}], "type_ref": "builtins.list"}}}, "HEADERS": {".class": "SymbolTableNode", "kind": "Gdef", "node": {".class": "Var", "flags": ["is_inferred", "has_explicit_value"], "fullname": "myutils.FILECONSTANTS.HEADERS", "name": "HEADERS", "type": {".class": "Instance", "args": [{".class": "AnyType", "missing_import_name": null, "source_any": null, "type_of_any": 4}, {".class": "AnyType", "missing_import_name": null, "source_any": null, "type_of_any": 4}], "type_ref": "builtins.dict"}}}, "INTERNALS": {".class": "SymbolTableNode", "kind": "Gdef", "node": {".class": "Var", "flags": ["is_inferred", "has_explicit_value"], "fullname": "myutils.FILECONSTANTS.INTERNALS", "name": "INTERNALS", "type": {".class": "AnyType", "missing_import_name": null, "source_any": {".class": "AnyType", "missing_import_name": null, "source_any": null, "type_of_any": 4}, "type_of_any": 7}}}, "__annotations__": {".class": "SymbolTableNode", "kind": "Gdef", "node": {".class": "Var", "flags": ["is_ready"], "fullname": "myutils.FILECONSTANTS.__annotations__", "name": "__annotations__", "type": {".class": "Instance", "args": ["builtins.str", {".class": "AnyType", "missing_import_name": null, "source_any": null, "type_of_any": 6}], "type_ref": "builtins.dict"}}}, "__doc__": {".class": "SymbolTableNode", "kind": "Gdef", "node": {".class": "Var", "flags": ["is_ready"], "fullname": "myutils.FILECONSTANTS.__doc__", "name": "__doc__", "type": "builtins.str"}}, "__file__": {".class": "SymbolTableNode", "kind": "Gdef", "node": {".class": "Var", "flags": ["is_ready"], "fullname": "myutils.FILECONSTANTS.__file__", "name": "__file__", "type": "builtins.str"}}, "__name__": {".class": "SymbolTableNode", "kind": "Gdef", "node": {".class": "Var", "flags": ["is_ready"], "fullname": "myutils.FILECONSTANTS.__name__", "name": "__name__", "type": "builtins.str"}}, "__package__": {".class": "SymbolTableNode", "kind": "Gdef", "node": {".class": "Var", "flags": ["is_ready"], "fullname": "myutils.FILECONSTANTS.__package__", "name": "__package__", "type": "builtins.str"}}, "ut": {".class": "SymbolTableNode", "cross_ref": "myutils.reductionutils", "kind": "Gdef"}}, "path": "x:\\myutils\\myutils\\FILECONSTANTS.py"}